simple_sdk/__init__.py
simple_sdk/client.py
simple_sdk/exceptions.py
simple_sdk/models.py
simple_sdk/utils.py
sachin_simple_sdk-0.1.0.dist-info/METADATA
sachin_simple_sdk-0.1.0.dist-info/WHEEL
sachin_simple_sdk-0.1.0.dist-info/RECORD
